{"title":"Resources","markdown":{"yaml":{"title":"Resources","editor":"visual"},"headingText":"Cloud Resources","containsRefs":false,"markdown":"\n\n\n## Flood\\@klaus\n\n2022-05-19: Connected via DataGrip (Add Postgres)\n\nHost: `118.138.244.154`\n\nUser: `limitedaccess`\n\nPW: on slack\n\n# Blogs/Wikis\n\n-   [Change detection with Raster Vision - azavea](https://www.azavea.com/blog/2022/04/18/change-detection-with-raster-vision/)\n-   [Resources on Remote Sensing on Climate Change AI](https://wiki.climatechange.ai/wiki/Remote_Sensing)\n\n# Course/Textbooks\n\n-   Python for Geospatial Data Analysis textbook -- check Monash Library\n-   [Intermediate Earth Data Science Textbook](https://www.earthdatascience.org/courses/use-data-open-source-python/)\n-   [Spatial Data Science (with applications in R), *Edzer Pebesma, Roger Bivand*](https://keen-swartz-3146c4.netlify.app) (2022)\n-   [*An Introduction to Spatial Data Analysis and Statistics: A Course in R*](https://paezha.github.io/spatial-analysis-r/front-matter.html#front-matter)*, Antonio Paez (2021)*\n-   [{terra} Tutorials and docs](https://rspatial.org/terra/index.html)\n-   [Spatio-Temporal Statistics with R](https://spacetimewithr.org/)\n-   [Applied Spatial Data Analysis with R](http://gis.humboldt.edu/OLM/r/Spatial%20Analysis%20With%20R.pdf)\n-   [Geocomputation with R](https://geocompr.robinlovelace.net/index.html)\n    -   [{mlr3} book subsection on spatio-temporal analysis](https://mlr3book.mlr-org.com/special-tasks.html#spatiotemporal)\n-   [ ] [{mlr3} vs {tidymodels}](https://pharmacoecon.me/post/2021-05-01-tidymodels-vs-mlr3/)\n-   Intro to GIS and Spatial Analysis, Manuel Gidmond\n    -   [Pitfalls to avoid](https://mgimond.github.io/Spatial/pitfalls-to-avoid.html)\n\n        -   patterns in non-uniform areal units\n\n### Spatial Database\n\n-   [ ] coursera video on [mosaic & aggregate](https://www.coursera.org/lecture/spatial-analysis-satellite-imagery-in-a-gis/mosaic-and-aggregate-tools-lKupP)\n-   [ ] [vignette by Edzer Pebsema](https://cran.r-project.org/web/packages/spacetime/vignettes/sto.pdf)\n-   [ ] [post by Paul Ramsey](http://blog.cleverelephant.ca/2021/05/indexes-and-queries.html)\n-   [ ] [spatial indices by Paul Ramsey](https://www.crunchydata.com/blog/the-many-spatial-indexes-of-postgis)\n-   [ ] [tutorial on tile_grid indexing](https://www.maptiler.com/google-maps-coordinates-tile-bounds-projection/#3/15.00/50.00)\n-   [ ] [grid generation in PostGIS](https://postgis.net/docs/ST_SquareGrid.html)\n\nMaybe\n\n-   [point grid creation with lots of code](https://gis.stackexchange.com/questions/4663/creating-regular-point-grid-inside-polygon-in-postgis/4672#4672)\n-   [Creating regular polygon grid in PostGIS](https://gis.stackexchange.com/questions/16374/creating-regular-polygon-grid-in-postgis)\n\n![](images/paste-F5BD97F2.png)\n\n# Relevant Software\n\nSee also <!--# TODO: link to infrastructure  -->\n\n-   R: `{rgee}` for accessing Google Earth Engine in R -- [cheatsheet](https://github.com/r-earthengine/cheatsheet)\n-   Python: `rasterio` for [pythonic API](https://rasterio.readthedocs.io/en/latest/quickstart.html) for raster manipulation in python (probably not needed)\n-   R:`{blockCV}` for generating spatially disjoint sets -- [paper](https://besjournals.onlinelibrary.wiley.com/doi/10.1111/2041-210X.13107), [github repo](https://github.com/rvalavi/blockCV) - [CRAN Task View: Analysis of Spatial Data](https://cran.r-project.org/web/views/Spatial.html)\n-   cli: {dvc} data version control\n    -   [R code and reproducible model development with DVC](https://dvc.org/blog/r-code-and-reproducible-model-development-with-dvc)\n\n# Code Cookbooks {#existing-code}\n\n-   [Survey of deep learning x satellite research with code](https://github.com/robmarkcole/satellite-image-deep-learning)\n-   [Python GDAL/OGR Cookbook](http://pcjericks.github.io/py-gdalogr-cookbook/index.html)\n\n# Research Tools\n\n-   [R Research Compendium Template](https://github.com/benmarwick/rrtools)\n\n-   [Git Repo structure for python ML paper](https://github.com/sodalabsio/vb_calibration_nn)\n\n## Reproducible Research\n\n-   [ ] Greg Wilson's [rules](https://third-bit.com/rules/) for research software and teaching\n-   [ ] [Research Software Engineering with Python](https://merely-useful.tech/py-rse/) course\n\n## Quarto + Rstudio Visual Mode\n\n### Blog Posts on Quarto\n\n-   https://www.apreshill.com/blog/2022-04-we-dont-talk-about-quarto/\n-   https://www.njtierney.com/post/2022/04/11/rmd-to-qmd/\n\n### 2022 Reproducible Authoring with Quarto - Mine Çetinkaya-Rundel\n\nTalk given at 2022 Toronto Workshop for Reproducibility\n\n📺 [Link to YouTube Recording](https://www.youtube.com/watch?v=6p4vOKS6Xls)\n\n-   [01:18](https://www.youtube.com/watch?v=6p4vOKS6Xls&t=78s) RMarkdown -\\> Quarto + live demo\n-   [04:16](https://www.youtube.com/watch?v=6p4vOKS6Xls&t=256s) RStudio Visual Editor -- removes some cognitive load of learning RMarkdown + coding, forward slash \"/\" to - insert anything\n-   [05:35](https://www.youtube.com/watch?v=6p4vOKS6Xls&t=335s) Quarto can render RMarkdown even if you just change the file extension\n-   [06:10](https://www.youtube.com/watch?v=6p4vOKS6Xls&t=370s) Shared features -- output: --\\> format:, live rendering, citations (from DOI search!), in-line R code\n-   [12:20](https://www.youtube.com/watch?v=6p4vOKS6Xls&t=740s) Quarto specific -- YAML style chunk options (great for alt text) but mixed style works!; global chunk - options in yaml header; code-link: true\n-   [16:18](https://www.youtube.com/watch?v=6p4vOKS6Xls&t=978s) Visual Editor helps with avoiding minutiae of markdown syntax -- alt-text, captions, links, tab-sets\n-   [18:13](https://www.youtube.com/watch?v=6p4vOKS6Xls&t=1093s) Change output from html to reveal.js slides -- \\`chalkboard: true\\` adds annotation tool; built-in - presentation tools\n-   [20:14](https://www.youtube.com/watch?v=6p4vOKS6Xls&t=1214s) more Quarto features-- R and python, support in other text editors, projects\n-   [24:15](https://www.youtube.com/watch?v=6p4vOKS6Xls&t=1455s) Q&A\n\n### R Markdown Advanced Tips to Become a Better Data Scientist & RStudio Connect \\| With Tom Mock\n\n📺[Link to YouTube Live Stream](https://www.youtube.com/watch?v=WkF7nqEYF1E)\n\n📋[Content Package Google Doc](https://docs.google.com/document/d/1VKGs1G9GcQcv4pCYFbK68_LDh72ODiZsIxXLN0z-zD4/edit)\n\n🧑‍💻[GitHub Repo](https://github.com/jthomasmock/penguin-project)\n\n-   [04:15](https://www.youtube.com/watch?v=WkF7nqEYF1E&t=255s) **Literate Programming**\n-   [09:00](https://www.youtube.com/watch?v=WkF7nqEYF1E&t=540s) - Rstudio Visual Editor Demo\n-   [15:44](https://www.youtube.com/watch?v=WkF7nqEYF1E&t=944s) - \\[🐍🔵\\] R and python in same document via {reticulate}\n-   [18:10](https://www.youtube.com/watch?v=WkF7nqEYF1E&t=1090s) - Q&A: Options for collaborative editing (version - control, shared drive etc.)\n-   [19:30](https://www.youtube.com/watch?v=WkF7nqEYF1E&t=1170s) - Q&A: Multi-pane support in Rstudio\n-   [20:46](https://www.youtube.com/watch?v=WkF7nqEYF1E&t=1246s) **Data Product (reports, presentations, dashboards, - websites etc.)**\n-   [24:15](https://www.youtube.com/watch?v=WkF7nqEYF1E&t=1455s) - Distill article\n-   [26:27](https://www.youtube.com/watch?v=WkF7nqEYF1E&t=1587s) - Xaringan presentation (add three dashes --- for - new slide)\n-   [28:58](https://www.youtube.com/watch?v=WkF7nqEYF1E&t=1738s) - Flexdashboard (with shiny)\n-   [30:30](https://www.youtube.com/watch?v=WkF7nqEYF1E&t=1830s) - \\[📉\\] Crosstalk (talk between different html widgets - instead of {shiny} server)\n-   [35:03](https://www.youtube.com/watch?v=WkF7nqEYF1E&t=2103s) - Q&A: Jobs panel -- parallelise render jobs in - background\n-   [36:50](https://www.youtube.com/watch?v=WkF7nqEYF1E&t=2210s) - Q&A: various data product packages, formats\n-   [39:35](https://www.youtube.com/watch?v=WkF7nqEYF1E&t=2375s) **Control Document (modularise data science tasks, - control code flow)**\n-   [39:58](https://www.youtube.com/watch?v=WkF7nqEYF1E&t=2398s) - \\[🧶\\] Knit with Parameters (YAML params: option)\n    -   documenting different models or datasets\n-   [41:20](https://www.youtube.com/watch?v=WkF7nqEYF1E&t=2480s) - Reference named chunks from .R files - (knitr::read_chunk())\n-   [43:00](https://www.youtube.com/watch?v=WkF7nqEYF1E&t=2580s) - Child Documents (reuse content, conditional - inclusion, {blastula} email)\n-   [47:07](https://www.youtube.com/watch?v=WkF7nqEYF1E&t=2827s) **Templating (don't repeat yourself)**\n-   [47:38](https://www.youtube.com/watch?v=WkF7nqEYF1E&t=2858s) - rmarkdown::render() with params, looping through - different param combinations\n-   [49:30](https://www.youtube.com/watch?v=WkF7nqEYF1E&t=2970s) - loop templates within a single document\n-   [50:40](https://www.youtube.com/watch?v=WkF7nqEYF1E&t=3040s) - 04-templating/ live code demo\n-   [54:37](https://www.youtube.com/watch?v=WkF7nqEYF1E&t=3277s) - {whisker} vs {glue} -- {{logic-less}} vs {logic - templating}\n-   [55:30](https://www.youtube.com/watch?v=WkF7nqEYF1E&t=3330s) - {whisker} for generating markdown files that you - can continue editing\n-   [57:49](https://www.youtube.com/watch?v=WkF7nqEYF1E&t=3469s) **RMarkdown + Rstudio Connect**\n-   [1:00:41](https://www.youtube.com/watch?v=WkF7nqEYF1E&t=3641s) Follow-up Reading and resources\n-   [1:04:49](https://www.youtube.com/watch?v=WkF7nqEYF1E&t=3889s) Q&A - {shiny} apps, {webshot2} for screenshots of - html, reading in multiple .R files, best practice for producing MSoffice files, {blastula}\n\nFor me:\n\n-   knit with params to document different model/hyper-parameter options <!--# TO DO NOTES!???-->\n-   interactive graphic for exploring Panel Maps with {crosstalk}\n-   Using R & Python in Rmarkdown (and hence Quarto)\n\n# R package Dev\n\nPackage Documentation\n\n-   [Blog post series by Maelle Salmon](https://blog.r-hub.io/tags/documentation/) covers vignettes, NEWS file, package manuals, URL checks, Internal Functions\n"},"formats":{"html":{"execute":{"fig-width":7,"fig-height":5,"fig-format":"retina","fig-dpi":96,"df-print":"default","error":false,"eval":true,"cache":null,"freeze":"auto","echo":true,"output":true,"warning":true,"include":true,"keep-md":false,"keep-ipynb":false,"ipynb":null,"enabled":null,"daemon":null,"daemon-restart":false,"debug":false,"ipynb-filters":[],"engine":"markdown"},"render":{"keep-tex":false,"keep-source":false,"keep-hidden":false,"prefer-html":false,"output-divs":true,"output-ext":"html","fig-align":"default","fig-pos":null,"fig-env":null,"code-fold":"none","code-overflow":"scroll","code-link":false,"code-line-numbers":false,"code-tools":false,"tbl-colwidths":"auto","merge-includes":true,"latex-auto-mk":true,"latex-auto-install":true,"latex-clean":true,"latex-max-runs":10,"latex-makeindex":"makeindex","latex-makeindex-opts":[],"latex-tlmgr-opts":[],"latex-input-paths":[],"latex-output-dir":null,"link-external-icon":false,"link-external-newwindow":false,"self-contained-math":false,"format-resources":[]},"pandoc":{"standalone":true,"wrap":"none","default-image-extension":"png","to":"html","css":["styles.css"],"toc":true,"from":"markdown+emoji","output-file":"resources.html"},"language":{},"metadata":{"lang":"en","fig-responsive":true,"quarto-version":"1.2.335","bibliography":["../references.bib"],"theme":"cosmo","title":"Resources","editor":"visual"},"extensions":{"book":{"multiFile":true}}}}}